openhands/README.md
openhands/__init__.py
openhands/agenthub/README.md
openhands/agenthub/__init__.py
openhands/agenthub/browsing_agent/README.md
openhands/agenthub/browsing_agent/__init__.py
openhands/agenthub/browsing_agent/browsing_agent.py
openhands/agenthub/browsing_agent/response_parser.py
openhands/agenthub/browsing_agent/utils.py
openhands/agenthub/codeact_agent/README.md
openhands/agenthub/codeact_agent/__init__.py
openhands/agenthub/codeact_agent/codeact_agent.py
openhands/agenthub/codeact_agent/function_calling.py
openhands/agenthub/codeact_agent/prompts/additional_info.j2
openhands/agenthub/codeact_agent/prompts/in_context_learning_example.j2
openhands/agenthub/codeact_agent/prompts/in_context_learning_example_suffix.j2
openhands/agenthub/codeact_agent/prompts/microagent_info.j2
openhands/agenthub/codeact_agent/prompts/security_risk_assessment.j2
openhands/agenthub/codeact_agent/prompts/system_prompt.j2
openhands/agenthub/codeact_agent/prompts/system_prompt_interactive.j2
openhands/agenthub/codeact_agent/prompts/system_prompt_long_horizon.j2
openhands/agenthub/codeact_agent/prompts/system_prompt_tech_philosophy.j2
openhands/agenthub/codeact_agent/prompts/user_prompt.j2
openhands/agenthub/codeact_agent/tools/__init__.py
openhands/agenthub/codeact_agent/tools/bash.py
openhands/agenthub/codeact_agent/tools/browser.py
openhands/agenthub/codeact_agent/tools/condensation_request.py
openhands/agenthub/codeact_agent/tools/finish.py
openhands/agenthub/codeact_agent/tools/ipython.py
openhands/agenthub/codeact_agent/tools/llm_based_edit.py
openhands/agenthub/codeact_agent/tools/prompt.py
openhands/agenthub/codeact_agent/tools/security_utils.py
openhands/agenthub/codeact_agent/tools/str_replace_editor.py
openhands/agenthub/codeact_agent/tools/task_tracker.py
openhands/agenthub/codeact_agent/tools/think.py
openhands/agenthub/dummy_agent/__init__.py
openhands/agenthub/dummy_agent/agent.py
openhands/agenthub/loc_agent/README.md
openhands/agenthub/loc_agent/__init__.py
openhands_ai-1.2.0.dist-info/METADATA
openhands_ai-1.2.0.dist-info/WHEEL
openhands_ai-1.2.0.dist-info/licenses/LICENSE
openhands_ai-1.2.0.dist-info/RECORD
