Metadata-Version: 2.4
Name: openhands-ai
Version: 1.2.0
Summary: OpenHands: Code Less, Make More
License-Expression: MIT
License-File: LICENSE
Author: OpenHands
Author-email: contact@all-hands.dev
Requires-Python: >=3.12,<3.14
Classifier: Programming Language :: Python :: 3 :: Only
Classifier: Programming Language :: Python :: 3.12
Classifier: Programming Language :: Python :: 3.13
Provides-Extra: third-party-runtimes
Requires-Dist: aiohttp (>=3.9,!=3.11.13)
Requires-Dist: anthropic[vertex]
Requires-Dist: anyio (==4.9)
Requires-Dist: asyncpg (>=0.30)
Requires-Dist: bashlex (>=0.18)
Requires-Dist: boto3
Requires-Dist: browsergym-core (==0.13.3)
Requires-Dist: daytona (==0.24.2) ; extra == "third-party-runtimes"
Requires-Dist: deprecated
Requires-Dist: deprecation (>=2.1)
Requires-Dist: dirhash
Requires-Dist: docker
Requires-Dist: e2b-code-interpreter (>=2) ; extra == "third-party-runtimes"
Requires-Dist: fastapi
Requires-Dist: fastmcp (>=2.12.4)
Requires-Dist: google-api-python-client (>=2.164)
Requires-Dist: google-auth-httplib2
Requires-Dist: google-auth-oauthlib
Requires-Dist: google-cloud-aiplatform
Requires-Dist: google-genai
Requires-Dist: html2text
Requires-Dist: httpx-aiohttp (>=0.1.8)
Requires-Dist: ipywidgets (>=8.1.5)
Requires-Dist: jinja2 (>=3.1.6)
Requires-Dist: joblib
Requires-Dist: json-repair
Requires-Dist: jupyter-kernel-gateway
Requires-Dist: kubernetes (>=33.1)
Requires-Dist: libtmux (>=0.46.2)
Requires-Dist: litellm (>=1.74.3)
Requires-Dist: lmnr (>=0.7.20)
Requires-Dist: memory-profiler (>=0.61)
Requires-Dist: modal (>=0.66.26,<1.2) ; extra == "third-party-runtimes"
Requires-Dist: numpy
Requires-Dist: openai (==2.8)
Requires-Dist: openhands-aci (==0.3.2)
Requires-Dist: openhands-agent-server (==1.8.1)
Requires-Dist: openhands-sdk (==1.8.1)
Requires-Dist: openhands-tools (==1.8.1)
Requires-Dist: opentelemetry-api (>=1.33.1)
Requires-Dist: opentelemetry-exporter-otlp-proto-grpc (>=1.33.1)
Requires-Dist: pathspec (>=0.12.1)
Requires-Dist: pexpect
Requires-Dist: pg8000 (>=1.31.5)
Requires-Dist: pillow (>=11.3)
Requires-Dist: playwright (>=1.55)
Requires-Dist: poetry (>=2.1.2)
Requires-Dist: prompt-toolkit (>=3.0.50)
Requires-Dist: protobuf (>=5,<6)
Requires-Dist: psutil
Requires-Dist: pybase62 (>=1)
Requires-Dist: pygithub (>=2.5)
Requires-Dist: pyjwt (>=2.9)
Requires-Dist: pylatexenc
Requires-Dist: pypdf (>=6)
Requires-Dist: python-docx
Requires-Dist: python-dotenv
Requires-Dist: python-frontmatter (>=1.1)
Requires-Dist: python-jose[cryptography] (>=3.3)
Requires-Dist: python-json-logger (>=3.2.1)
Requires-Dist: python-multipart
Requires-Dist: python-pptx
Requires-Dist: python-socketio (>=5.11.4)
Requires-Dist: pythonnet
Requires-Dist: pyyaml (>=6.0.2)
Requires-Dist: qtconsole (>=5.6.1)
Requires-Dist: rapidfuzz (>=3.9)
Requires-Dist: redis (>=5.2,<7)
Requires-Dist: requests (>=2.32.5)
Requires-Dist: runloop-api-client (==0.50) ; extra == "third-party-runtimes"
Requires-Dist: setuptools (>=78.1.1)
Requires-Dist: shellingham (>=1.5.4)
Requires-Dist: sqlalchemy[asyncio] (>=2.0.40)
Requires-Dist: sse-starlette (>=3.0.2)
Requires-Dist: starlette (>=0.48)
Requires-Dist: tenacity (>=8.5,<10)
Requires-Dist: termcolor
Requires-Dist: toml
Requires-Dist: tornado (>=6.5)
Requires-Dist: types-toml
Requires-Dist: urllib3 (>=2.6.3)
Requires-Dist: uvicorn
Requires-Dist: whatthepatch (>=1.0.6)
Requires-Dist: zope-interface (==7.2)
Project-URL: Homepage, https://github.com/OpenHands/OpenHands
Project-URL: Repository, https://github.com/OpenHands/OpenHands
